Metadata-Version: 2.1
Name: minigrad
Version: 0.0.6
Summary: Autograd Engine written in Python C-API
Home-page: https://github.com/goktug97/minigrad
Author: Göktuğ Karakaşlı
Author-email: karakasligk@gmail.com
License: MIT
Platform: UNKNOWN
Classifier: Programming Language :: Python :: 3
Classifier: License :: OSI Approved :: MIT License
Classifier: Operating System :: OS Independent
Requires-Python: >=3.6
